README.rst
evergreen.zip
screenshot.png
setup.py
docs/HISTORY.txt
docs/INSTALL.txt
docs/LICENSE.GPL
docs/LICENSE.txt
plonetheme/__init__.py
plonetheme.evergreen.egg-info/PKG-INFO
plonetheme.evergreen.egg-info/SOURCES.txt
plonetheme.evergreen.egg-info/dependency_links.txt
plonetheme.evergreen.egg-info/entry_points.txt
plonetheme.evergreen.egg-info/namespace_packages.txt
plonetheme.evergreen.egg-info/requires.txt
plonetheme.evergreen.egg-info/top_level.txt
plonetheme/evergreen/__init__.py
plonetheme/evergreen/configure.zcml
plonetheme/evergreen/profiles/default/metadata.xml
plonetheme/evergreen/profiles/default/theme.xml
plonetheme/evergreen/static/default.css
plonetheme/evergreen/static/index.html
plonetheme/evergreen/static/license.txt
plonetheme/evergreen/static/manifest.cfg
plonetheme/evergreen/static/plone-integration.css
plonetheme/evergreen/static/rules.xml
plonetheme/evergreen/static/images/img1.gif
plonetheme/evergreen/static/images/img2.jpg